ovos_skill_filebrowser-0.0.2.data/data/share/applications/skill-ovos-filebrowser.desktop
ovos_skill_filebrowser-0.0.2.data/data/share/icons/ovos-file-browser.svg
skill_ovos_filebrowser/LICENSE
skill_ovos_filebrowser/MANIFEST.in
skill_ovos_filebrowser/README.md
skill_ovos_filebrowser/__init__.py
skill_ovos_filebrowser/notify-requirements.txt
skill_ovos_filebrowser/requirements.txt
skill_ovos_filebrowser/version.py
skill_ovos_filebrowser/locale/de-de/intents/open.file.browser.intent
skill_ovos_filebrowser/locale/en-us/open.file.browser.intent
skill_ovos_filebrowser/locale/en-us/intents/open.file.browser.intent
skill_ovos_filebrowser/locale/es-es/intents/open.file.browser.intent
skill_ovos_filebrowser/locale/fr-fr/intents/open.file.browser.intent
skill_ovos_filebrowser/locale/it-it/intents/open.file.browser.intent
skill_ovos_filebrowser/locale/pt-pt/intents/open.file.browser.intent
skill_ovos_filebrowser/ovos_skill_filebrowser.egg-info/PKG-INFO
skill_ovos_filebrowser/ovos_skill_filebrowser.egg-info/SOURCES.txt
skill_ovos_filebrowser/ovos_skill_filebrowser.egg-info/dependency_links.txt
skill_ovos_filebrowser/ovos_skill_filebrowser.egg-info/entry_points.txt
skill_ovos_filebrowser/ovos_skill_filebrowser.egg-info/requires.txt
skill_ovos_filebrowser/ovos_skill_filebrowser.egg-info/top_level.txt
skill_ovos_filebrowser/res/desktop/skill-ovos-filebrowser.desktop
skill_ovos_filebrowser/res/desktop/skill.json
skill_ovos_filebrowser/res/icon/ovos-file-browser.svg
skill_ovos_filebrowser/ui/Browser.qml
skill_ovos_filebrowser/ui/BrowserView.qml
skill_ovos_filebrowser/ui/ControllerArea.qml
skill_ovos_filebrowser/ui/FileItemDelegate.qml
skill_ovos_filebrowser/ui/ImageViewer.qml
skill_ovos_filebrowser/ui/KdeConnectDevices.qml
skill_ovos_filebrowser/ui/MenuButton.qml
skill_ovos_filebrowser/ui/PlacesView.qml
skill_ovos_filebrowser/ui/ShareButton.qml
skill_ovos_filebrowser/ui/images/generic-audio-bg.jpg
skill_ovos_filebrowser/ui/images/share-bluetooth.svg
skill_ovos_filebrowser/ui/images/share-kdeconnect.png
skill_ovos_filebrowser/ui/sounds/clicked.wav
ovos_skill_filebrowser-0.0.2.dist-info/LICENSE
ovos_skill_filebrowser-0.0.2.dist-info/METADATA
ovos_skill_filebrowser-0.0.2.dist-info/WHEEL
ovos_skill_filebrowser-0.0.2.dist-info/entry_points.txt
ovos_skill_filebrowser-0.0.2.dist-info/top_level.txt
ovos_skill_filebrowser-0.0.2.dist-info/RECORD
