Metadata-Version: 2.1
Name: ovos-skill-filebrowser
Version: 0.0.2
Summary: OVOS file browser skill plugin
Home-page: https://github.com/OpenVoiceOS/skill-ovos-filebrowser
Author: Aix
Author-email: aix.m@outlook.com
License: Apache-2.0
Keywords: ovos file browser skill plugin
Platform: UNKNOWN
Requires-Dist: ovos-utils (>=0.0.28,~=0.0)
Requires-Dist: ovos-workshop (>=0.0.11,~=0.0)
Provides-Extra: notify
Requires-Dist: pyudev ; extra == 'notify'
